{
  "annotations": {
    "list": [
      {
        "builtIn": 1,
        "datasource": {
          "type": "grafana",
          "uid": "-- Grafana --"
        },
        "enable": true,
        "hide": true,
        "iconColor": "rgba(0, 211, 255, 1)",
        "name": "Annotations & Alerts",
        "type": "dashboard"
      }
    ]
  },
  "editable": true,
  "fiscalYearStartMonth": 0,
  "graphTooltip": 1,
  "id": null,
  "links": [],
  "liveNow": true,
  "panels": [
    {
      "datasource": {
        "type": "prometheus",
        "uid": "prometheus"
      },
      "description": "Snapshot of average resolved markout, fill count, and resolution rate by strategy side, pivoted across 0s, 30s, 60s, and 120s horizons.",
      "fieldConfig": {
        "defaults": {
          "custom": {
            "align": "auto",
            "cellOptions": {
              "type": "auto"
            },
            "inspect": false
          },
          "mappings": [],
          "thresholds": {
            "mode": "absolute",
            "steps": [
              {
                "color": "green",
                "value": null
              }
            ]
          }
        },
        "overrides": [
          {
            "matcher": {
              "id": "byName",
              "options": "Strategy | Side"
            },
            "properties": [
              {
                "id": "custom.width",
                "value": 360
              }
            ]
          },
          {
            "matcher": {
              "id": "byRegexp",
              "options": ".* Avg$"
            },
            "properties": [
              {
                "id": "unit",
                "value": "none"
              },
              {
                "id": "custom.cellOptions",
                "value": {
                  "type": "color-background"
                }
              },
              {
                "id": "thresholds",
                "value": {
                  "mode": "absolute",
                  "steps": [
                    {
                      "color": "red",
                      "value": null
                    },
                    {
                      "color": "green",
                      "value": 0
                    }
                  ]
                }
              }
            ]
          },
          {
            "matcher": {
              "id": "byRegexp",
              "options": ".* N$"
            },
            "properties": [
              {
                "id": "unit",
                "value": "short"
              }
            ]
          },
          {
            "matcher": {
              "id": "byRegexp",
              "options": ".* Res%$"
            },
            "properties": [
              {
                "id": "unit",
                "value": "percentunit"
              }
            ]
          }
        ]
      },
      "gridPos": {
        "h": 10,
        "w": 24,
        "x": 0,
        "y": 0
      },
      "id": 1,
      "options": {
        "cellHeight": "sm",
        "footer": {
          "countRows": false,
          "fields": "",
          "reducer": [
            "sum"
          ],
          "show": false
        },
        "showHeader": true
      },
      "pluginVersion": "10.2.3",
      "targets": [
        {
          "datasource": {
            "type": "prometheus",
            "uid": "prometheus"
          },
          "expr": "label_join(avg by (strategy_id,order_side) (tokenmm_markout_avg_bps{env=~\"$env\",profile=~\"$profile\",strategy_id=~\"$strategy_id\",venue=~\"$venue\",symbol=~\"$symbol\",order_side=~\"$order_side\",benchmark_name=~\"$benchmark_name\",analysis_window=~\"$window\",horizon_s=\"0\"}), \"series_key\", \" | \", \"strategy_id\", \"order_side\")",
          "format": "table",
          "instant": true,
          "legendFormat": "0s Avg",
          "refId": "A"
        },
        {
          "datasource": {
            "type": "prometheus",
            "uid": "prometheus"
          },
          "expr": "label_join(avg by (strategy_id,order_side) (tokenmm_markout_avg_bps{env=~\"$env\",profile=~\"$profile\",strategy_id=~\"$strategy_id\",venue=~\"$venue\",symbol=~\"$symbol\",order_side=~\"$order_side\",benchmark_name=~\"$benchmark_name\",analysis_window=~\"$window\",horizon_s=\"30\"}), \"series_key\", \" | \", \"strategy_id\", \"order_side\")",
          "format": "table",
          "instant": true,
          "legendFormat": "30s Avg",
          "refId": "B"
        },
        {
          "datasource": {
            "type": "prometheus",
            "uid": "prometheus"
          },
          "expr": "label_join(avg by (strategy_id,order_side) (tokenmm_markout_avg_bps{env=~\"$env\",profile=~\"$profile\",strategy_id=~\"$strategy_id\",venue=~\"$venue\",symbol=~\"$symbol\",order_side=~\"$order_side\",benchmark_name=~\"$benchmark_name\",analysis_window=~\"$window\",horizon_s=\"60\"}), \"series_key\", \" | \", \"strategy_id\", \"order_side\")",
          "format": "table",
          "instant": true,
          "legendFormat": "60s Avg",
          "refId": "C"
        },
        {
          "datasource": {
            "type": "prometheus",
            "uid": "prometheus"
          },
          "expr": "label_join(avg by (strategy_id,order_side) (tokenmm_markout_avg_bps{env=~\"$env\",profile=~\"$profile\",strategy_id=~\"$strategy_id\",venue=~\"$venue\",symbol=~\"$symbol\",order_side=~\"$order_side\",benchmark_name=~\"$benchmark_name\",analysis_window=~\"$window\",horizon_s=\"120\"}), \"series_key\", \" | \", \"strategy_id\", \"order_side\")",
          "format": "table",
          "instant": true,
          "legendFormat": "120s Avg",
          "refId": "D"
        },
        {
          "datasource": {
            "type": "prometheus",
            "uid": "prometheus"
          },
          "expr": "label_join(max by (strategy_id,order_side) (tokenmm_markout_fill_count{env=~\"$env\",profile=~\"$profile\",strategy_id=~\"$strategy_id\",venue=~\"$venue\",symbol=~\"$symbol\",order_side=~\"$order_side\",benchmark_name=~\"$benchmark_name\",analysis_window=~\"$window\",horizon_s=\"0\"}), \"series_key\", \" | \", \"strategy_id\", \"order_side\")",
          "format": "table",
          "instant": true,
          "legendFormat": "0s N",
          "refId": "E"
        },
        {
          "datasource": {
            "type": "prometheus",
            "uid": "prometheus"
          },
          "expr": "label_join(max by (strategy_id,order_side) (tokenmm_markout_fill_count{env=~\"$env\",profile=~\"$profile\",strategy_id=~\"$strategy_id\",venue=~\"$venue\",symbol=~\"$symbol\",order_side=~\"$order_side\",benchmark_name=~\"$benchmark_name\",analysis_window=~\"$window\",horizon_s=\"30\"}), \"series_key\", \" | \", \"strategy_id\", \"order_side\")",
          "format": "table",
          "instant": true,
          "legendFormat": "30s N",
          "refId": "F"
        },
        {
          "datasource": {
            "type": "prometheus",
            "uid": "prometheus"
          },
          "expr": "label_join(max by (strategy_id,order_side) (tokenmm_markout_fill_count{env=~\"$env\",profile=~\"$profile\",strategy_id=~\"$strategy_id\",venue=~\"$venue\",symbol=~\"$symbol\",order_side=~\"$order_side\",benchmark_name=~\"$benchmark_name\",analysis_window=~\"$window\",horizon_s=\"60\"}), \"series_key\", \" | \", \"strategy_id\", \"order_side\")",
          "format": "table",
          "instant": true,
          "legendFormat": "60s N",
          "refId": "G"
        },
        {
          "datasource": {
            "type": "prometheus",
            "uid": "prometheus"
          },
          "expr": "label_join(max by (strategy_id,order_side) (tokenmm_markout_fill_count{env=~\"$env\",profile=~\"$profile\",strategy_id=~\"$strategy_id\",venue=~\"$venue\",symbol=~\"$symbol\",order_side=~\"$order_side\",benchmark_name=~\"$benchmark_name\",analysis_window=~\"$window\",horizon_s=\"120\"}), \"series_key\", \" | \", \"strategy_id\", \"order_side\")",
          "format": "table",
          "instant": true,
          "legendFormat": "120s N",
          "refId": "H"
        },
        {
          "datasource": {
            "type": "prometheus",
            "uid": "prometheus"
          },
          "expr": "label_join(avg by (strategy_id,order_side) (tokenmm_markout_resolution_rate{env=~\"$env\",profile=~\"$profile\",strategy_id=~\"$strategy_id\",venue=~\"$venue\",symbol=~\"$symbol\",order_side=~\"$order_side\",benchmark_name=~\"$benchmark_name\",analysis_window=~\"$window\",horizon_s=\"0\"}), \"series_key\", \" | \", \"strategy_id\", \"order_side\")",
          "format": "table",
          "instant": true,
          "legendFormat": "0s Res%",
          "refId": "I"
        },
        {
          "datasource": {
            "type": "prometheus",
            "uid": "prometheus"
          },
          "expr": "label_join(avg by (strategy_id,order_side) (tokenmm_markout_resolution_rate{env=~\"$env\",profile=~\"$profile\",strategy_id=~\"$strategy_id\",venue=~\"$venue\",symbol=~\"$symbol\",order_side=~\"$order_side\",benchmark_name=~\"$benchmark_name\",analysis_window=~\"$window\",horizon_s=\"30\"}), \"series_key\", \" | \", \"strategy_id\", \"order_side\")",
          "format": "table",
          "instant": true,
          "legendFormat": "30s Res%",
          "refId": "J"
        },
        {
          "datasource": {
            "type": "prometheus",
            "uid": "prometheus"
          },
          "expr": "label_join(avg by (strategy_id,order_side) (tokenmm_markout_resolution_rate{env=~\"$env\",profile=~\"$profile\",strategy_id=~\"$strategy_id\",venue=~\"$venue\",symbol=~\"$symbol\",order_side=~\"$order_side\",benchmark_name=~\"$benchmark_name\",analysis_window=~\"$window\",horizon_s=\"60\"}), \"series_key\", \" | \", \"strategy_id\", \"order_side\")",
          "format": "table",
          "instant": true,
          "legendFormat": "60s Res%",
          "refId": "K"
        },
        {
          "datasource": {
            "type": "prometheus",
            "uid": "prometheus"
          },
          "expr": "label_join(avg by (strategy_id,order_side) (tokenmm_markout_resolution_rate{env=~\"$env\",profile=~\"$profile\",strategy_id=~\"$strategy_id\",venue=~\"$venue\",symbol=~\"$symbol\",order_side=~\"$order_side\",benchmark_name=~\"$benchmark_name\",analysis_window=~\"$window\",horizon_s=\"120\"}), \"series_key\", \" | \", \"strategy_id\", \"order_side\")",
          "format": "table",
          "instant": true,
          "legendFormat": "120s Res%",
          "refId": "L"
        }
      ],
      "title": "Strategy + Side Snapshot",
      "transformations": [
        {
          "id": "joinByField",
          "options": {
            "byField": "series_key",
            "mode": "outer"
          }
        },
        {
          "id": "organize",
          "options": {
            "excludeByName": {
              "Time": true,
              "Time 1": true,
              "Time 2": true,
              "Time 3": true,
              "Time 4": true,
              "Time 5": true,
              "Time 6": true,
              "Time 7": true,
              "Time 8": true,
              "Time 9": true,
              "Time 10": true,
              "Time 11": true,
              "__name__": true,
              "__name__ 1": true,
              "__name__ 2": true,
              "__name__ 3": true,
              "__name__ 4": true,
              "__name__ 5": true,
              "__name__ 6": true,
              "__name__ 7": true,
              "__name__ 8": true,
              "__name__ 9": true,
              "__name__ 10": true,
              "__name__ 11": true,
              "order_side": true,
              "order_side 1": true,
              "order_side 2": true,
              "order_side 3": true,
              "order_side 4": true,
              "order_side 5": true,
              "order_side 6": true,
              "order_side 7": true,
              "order_side 8": true,
              "order_side 9": true,
              "order_side 10": true,
              "order_side 11": true,
              "strategy_id": true,
              "strategy_id 1": true,
              "strategy_id 2": true,
              "strategy_id 3": true,
              "strategy_id 4": true,
              "strategy_id 5": true,
              "strategy_id 6": true,
              "strategy_id 7": true,
              "strategy_id 8": true,
              "strategy_id 9": true,
              "strategy_id 10": true,
              "strategy_id 11": true
            },
            "indexByName": {
              "series_key": 0,
              "Value #A": 1,
              "Value #B": 2,
              "Value #C": 3,
              "Value #D": 4,
              "Value #E": 5,
              "Value #F": 6,
              "Value #G": 7,
              "Value #H": 8,
              "Value #I": 9,
              "Value #J": 10,
              "Value #K": 11,
              "Value #L": 12
            },
            "renameByName": {
              "Value #A": "0s Avg",
              "Value #B": "30s Avg",
              "Value #C": "60s Avg",
              "Value #D": "120s Avg",
              "Value #E": "0s N",
              "Value #F": "30s N",
              "Value #G": "60s N",
              "Value #H": "120s N",
              "Value #I": "0s Res%",
              "Value #J": "30s Res%",
              "Value #K": "60s Res%",
              "Value #L": "120s Res%",
              "series_key": "Strategy | Side"
            }
          }
        }
      ],
      "type": "table"
    },
    {
      "datasource": {
        "type": "prometheus",
        "uid": "prometheus"
      },
      "description": "Rolling markout series over the selected window and dashboard time range.",
      "fieldConfig": {
        "defaults": {
          "color": {
            "mode": "palette-classic"
          },
          "custom": {
            "axisCenteredZero": true,
            "drawStyle": "line",
            "fillOpacity": 10,
            "lineInterpolation": "linear",
            "lineWidth": 2,
            "showPoints": "never"
          },
          "mappings": [],
          "thresholds": {
            "mode": "absolute",
            "steps": [
              {
                "color": "red",
                "value": null
              },
              {
                "color": "green",
                "value": 0
              }
            ]
          },
          "unit": "none"
        },
        "overrides": []
      },
      "gridPos": {
        "h": 8,
        "w": 24,
        "x": 0,
        "y": 10
      },
      "id": 2,
      "options": {
        "legend": {
          "calcs": [],
          "displayMode": "list",
          "placement": "bottom"
        },
        "tooltip": {
          "mode": "multi"
        }
      },
      "targets": [
        {
          "datasource": {
            "type": "prometheus",
            "uid": "prometheus"
          },
          "expr": "tokenmm_markout_avg_bps{env=~\"$env\",profile=~\"$profile\",strategy_id=~\"$strategy_id\",venue=~\"$venue\",symbol=~\"$symbol\",order_side=~\"$order_side\",horizon_s=~\"$horizon_s\",benchmark_name=~\"$benchmark_name\",analysis_window=~\"$window\"}",
          "legendFormat": "Avg {{strategy_id}} {{venue}} {{symbol}} {{benchmark_name}} {{horizon_s}}s {{order_side}}",
          "refId": "A"
        },
        {
          "datasource": {
            "type": "prometheus",
            "uid": "prometheus"
          },
          "expr": "tokenmm_markout_nw_bps{env=~\"$env\",profile=~\"$profile\",strategy_id=~\"$strategy_id\",venue=~\"$venue\",symbol=~\"$symbol\",order_side=~\"$order_side\",horizon_s=~\"$horizon_s\",benchmark_name=~\"$benchmark_name\",analysis_window=~\"$window\"}",
          "legendFormat": "NW {{strategy_id}} {{venue}} {{symbol}} {{benchmark_name}} {{horizon_s}}s {{order_side}}",
          "refId": "B"
        }
      ],
      "title": "Rolling Markout Bps",
      "type": "timeseries"
    },
    {
      "datasource": {
        "type": "prometheus",
        "uid": "prometheus"
      },
      "description": "Rolling resolution rate over the selected window and dashboard time range.",
      "fieldConfig": {
        "defaults": {
          "color": {
            "mode": "palette-classic"
          },
          "custom": {
            "axisCenteredZero": false,
            "drawStyle": "line",
            "fillOpacity": 10,
            "lineInterpolation": "linear",
            "lineWidth": 2,
            "showPoints": "never"
          },
          "mappings": [],
          "thresholds": {
            "mode": "absolute",
            "steps": [
              {
                "color": "red",
                "value": null
              },
              {
                "color": "yellow",
                "value": 0.25
              },
              {
                "color": "green",
                "value": 0.5
              }
            ]
          },
          "unit": "percentunit"
        },
        "overrides": []
      },
      "gridPos": {
        "h": 8,
        "w": 12,
        "x": 0,
        "y": 18
      },
      "id": 3,
      "options": {
        "legend": {
          "calcs": [],
          "displayMode": "list",
          "placement": "bottom"
        },
        "tooltip": {
          "mode": "multi"
        }
      },
      "targets": [
        {
          "datasource": {
            "type": "prometheus",
            "uid": "prometheus"
          },
          "expr": "tokenmm_markout_resolution_rate{env=~\"$env\",profile=~\"$profile\",strategy_id=~\"$strategy_id\",venue=~\"$venue\",symbol=~\"$symbol\",order_side=~\"$order_side\",horizon_s=~\"$horizon_s\",benchmark_name=~\"$benchmark_name\",analysis_window=~\"$window\"}",
          "legendFormat": "Resolution {{strategy_id}} {{venue}} {{symbol}} {{benchmark_name}} {{horizon_s}}s {{order_side}}",
          "refId": "A"
        }
      ],
      "title": "Rolling Resolution Rate",
      "type": "timeseries"
    },
    {
      "datasource": {
        "type": "prometheus",
        "uid": "prometheus"
      },
      "description": "Rolling fill coverage over the selected window and dashboard time range.",
      "fieldConfig": {
        "defaults": {
          "color": {
            "mode": "palette-classic"
          },
          "custom": {
            "axisCenteredZero": false,
            "drawStyle": "line",
            "fillOpacity": 10,
            "lineInterpolation": "linear",
            "lineWidth": 2,
            "showPoints": "never"
          },
          "mappings": [],
          "thresholds": {
            "mode": "absolute",
            "steps": [
              {
                "color": "green",
                "value": null
              }
            ]
          },
          "unit": "short"
        },
        "overrides": []
      },
      "gridPos": {
        "h": 8,
        "w": 12,
        "x": 12,
        "y": 18
      },
      "id": 4,
      "options": {
        "legend": {
          "calcs": [],
          "displayMode": "list",
          "placement": "bottom"
        },
        "tooltip": {
          "mode": "multi"
        }
      },
      "targets": [
        {
          "datasource": {
            "type": "prometheus",
            "uid": "prometheus"
          },
          "expr": "tokenmm_markout_fill_count{env=~\"$env\",profile=~\"$profile\",strategy_id=~\"$strategy_id\",venue=~\"$venue\",symbol=~\"$symbol\",order_side=~\"$order_side\",horizon_s=~\"$horizon_s\",benchmark_name=~\"$benchmark_name\",analysis_window=~\"$window\"}",
          "legendFormat": "Fill Count {{strategy_id}} {{venue}} {{symbol}} {{benchmark_name}} {{horizon_s}}s {{order_side}}",
          "refId": "A"
        },
        {
          "datasource": {
            "type": "prometheus",
            "uid": "prometheus"
          },
          "expr": "tokenmm_markout_resolved_rows{env=~\"$env\",profile=~\"$profile\",strategy_id=~\"$strategy_id\",venue=~\"$venue\",symbol=~\"$symbol\",order_side=~\"$order_side\",horizon_s=~\"$horizon_s\",benchmark_name=~\"$benchmark_name\",analysis_window=~\"$window\"}",
          "legendFormat": "Resolved Rows {{strategy_id}} {{venue}} {{symbol}} {{benchmark_name}} {{horizon_s}}s {{order_side}}",
          "refId": "B"
        }
      ],
      "title": "Fill Coverage",
      "type": "timeseries"
    },
    {
      "datasource": {
        "type": "prometheus",
        "uid": "prometheus"
      },
      "description": "Age of the most recent target timestamp for the selected series.",
      "fieldConfig": {
        "defaults": {
          "color": {
            "mode": "palette-classic"
          },
          "custom": {
            "axisCenteredZero": false,
            "drawStyle": "line",
            "fillOpacity": 10,
            "lineInterpolation": "linear",
            "lineWidth": 2,
            "showPoints": "never"
          },
          "mappings": [],
          "thresholds": {
            "mode": "absolute",
            "steps": [
              {
                "color": "green",
                "value": null
              },
              {
                "color": "yellow",
                "value": 180
              },
              {
                "color": "red",
                "value": 600
              }
            ]
          },
          "unit": "s"
        },
        "overrides": []
      },
      "gridPos": {
        "h": 8,
        "w": 24,
        "x": 0,
        "y": 26
      },
      "id": 5,
      "options": {
        "legend": {
          "calcs": [],
          "displayMode": "list",
          "placement": "bottom"
        },
        "tooltip": {
          "mode": "multi"
        }
      },
      "targets": [
        {
          "datasource": {
            "type": "prometheus",
            "uid": "prometheus"
          },
          "expr": "time() - tokenmm_markout_last_target_ts_seconds{env=~\"$env\",profile=~\"$profile\",strategy_id=~\"$strategy_id\",venue=~\"$venue\",symbol=~\"$symbol\",order_side=~\"$order_side\",horizon_s=~\"$horizon_s\",benchmark_name=~\"$benchmark_name\",analysis_window=~\"$window\"}",
          "legendFormat": "Age {{strategy_id}} {{venue}} {{symbol}} {{benchmark_name}} {{horizon_s}}s {{order_side}}",
          "refId": "A"
        }
      ],
      "title": "Last Target Age",
      "type": "timeseries"
    }
  ],
  "refresh": "30s",
  "schemaVersion": 39,
  "style": "dark",
  "tags": [
    "tokenmm",
    "markouts"
  ],
  "templating": {
    "list": [
      {
        "current": {
          "selected": true,
          "text": "prod",
          "value": "prod"
        },
        "hide": 0,
        "includeAll": false,
        "label": "env",
        "name": "env",
        "options": [
          {
            "selected": true,
            "text": "prod",
            "value": "prod"
          }
        ],
        "query": "prod",
        "type": "custom"
      },
      {
        "current": {
          "selected": true,
          "text": "tokenmm",
          "value": "tokenmm"
        },
        "hide": 0,
        "includeAll": false,
        "label": "profile",
        "name": "profile",
        "options": [
          {
            "selected": true,
            "text": "tokenmm",
            "value": "tokenmm"
          }
        ],
        "query": "tokenmm",
        "type": "custom"
      },
      {
        "allValue": ".*",
        "current": {
          "selected": true,
          "text": "All",
          "value": "$__all"
        },
        "datasource": {
          "type": "prometheus",
          "uid": "prometheus"
        },
        "definition": "label_values(tokenmm_markout_avg_bps{env=~\"$env\",profile=~\"$profile\",benchmark_name=~\"$benchmark_name\"}, strategy_id)",
        "hide": 0,
        "includeAll": true,
        "label": "strategy_id",
        "multi": true,
        "name": "strategy_id",
        "options": [
          {
            "selected": true,
            "text": "All",
            "value": "$__all"
          }
        ],
        "query": "label_values(tokenmm_markout_avg_bps{env=~\"$env\",profile=~\"$profile\",benchmark_name=~\"$benchmark_name\"}, strategy_id)",
        "refresh": 1,
        "regex": "",
        "sort": 1,
        "type": "query"
      },
      {
        "allValue": ".*",
        "current": {
          "selected": true,
          "text": "All",
          "value": "$__all"
        },
        "datasource": {
          "type": "prometheus",
          "uid": "prometheus"
        },
        "definition": "label_values(tokenmm_markout_avg_bps{env=~\"$env\",profile=~\"$profile\",strategy_id=~\"$strategy_id\",benchmark_name=~\"$benchmark_name\"}, venue)",
        "hide": 0,
        "includeAll": true,
        "label": "venue",
        "multi": true,
        "name": "venue",
        "options": [
          {
            "selected": true,
            "text": "All",
            "value": "$__all"
          }
        ],
        "query": "label_values(tokenmm_markout_avg_bps{env=~\"$env\",profile=~\"$profile\",strategy_id=~\"$strategy_id\",benchmark_name=~\"$benchmark_name\"}, venue)",
        "refresh": 1,
        "regex": "",
        "sort": 1,
        "type": "query"
      },
      {
        "allValue": ".*",
        "current": {
          "selected": true,
          "text": "All",
          "value": "$__all"
        },
        "datasource": {
          "type": "prometheus",
          "uid": "prometheus"
        },
        "definition": "label_values(tokenmm_markout_avg_bps{env=~\"$env\",profile=~\"$profile\",strategy_id=~\"$strategy_id\",venue=~\"$venue\",benchmark_name=~\"$benchmark_name\"}, symbol)",
        "hide": 0,
        "includeAll": true,
        "label": "symbol",
        "multi": true,
        "name": "symbol",
        "options": [
          {
            "selected": true,
            "text": "All",
            "value": "$__all"
          }
        ],
        "query": "label_values(tokenmm_markout_avg_bps{env=~\"$env\",profile=~\"$profile\",strategy_id=~\"$strategy_id\",venue=~\"$venue\",benchmark_name=~\"$benchmark_name\"}, symbol)",
        "refresh": 1,
        "regex": "",
        "sort": 1,
        "type": "query"
      },
      {
        "allValue": ".*",
        "current": {
          "selected": true,
          "text": "All",
          "value": "$__all"
        },
        "hide": 0,
        "includeAll": true,
        "label": "order_side",
        "multi": true,
        "name": "order_side",
        "options": [
          {
            "selected": true,
            "text": "All",
            "value": "$__all"
          },
          {
            "selected": false,
            "text": "BUY",
            "value": "BUY"
          },
          {
            "selected": false,
            "text": "SELL",
            "value": "SELL"
          }
        ],
        "query": "BUY,SELL",
        "type": "custom"
      },
      {
        "allValue": ".*",
        "current": {
          "selected": true,
          "text": "All",
          "value": "$__all"
        },
        "hide": 0,
        "includeAll": true,
        "label": "horizon_s",
        "multi": true,
        "name": "horizon_s",
        "options": [
          {
            "selected": true,
            "text": "All",
            "value": "$__all"
          },
          {
            "selected": false,
            "text": "0",
            "value": "0"
          },
          {
            "selected": false,
            "text": "30",
            "value": "30"
          },
          {
            "selected": false,
            "text": "60",
            "value": "60"
          },
          {
            "selected": false,
            "text": "120",
            "value": "120"
          }
        ],
        "query": "0,30,60,120",
        "type": "custom"
      },
      {
        "current": {
          "selected": true,
          "text": "fv_market_mid",
          "value": "fv_market_mid"
        },
        "hide": 0,
        "includeAll": false,
        "label": "benchmark_name",
        "multi": false,
        "name": "benchmark_name",
        "options": [
          {
            "selected": true,
            "text": "fv_market_mid",
            "value": "fv_market_mid"
          },
          {
            "selected": false,
            "text": "local_mkt_mid",
            "value": "local_mkt_mid"
          }
        ],
        "query": "fv_market_mid,local_mkt_mid",
        "type": "custom"
      },
      {
        "current": {
          "selected": true,
          "text": "2h",
          "value": "2h"
        },
        "hide": 0,
        "includeAll": false,
        "label": "window",
        "name": "window",
        "options": [
          {
            "selected": false,
            "text": "15m",
            "value": "15m"
          },
          {
            "selected": false,
            "text": "1h",
            "value": "1h"
          },
          {
            "selected": true,
            "text": "2h",
            "value": "2h"
          },
          {
            "selected": false,
            "text": "4h",
            "value": "4h"
          },
          {
            "selected": false,
            "text": "1d",
            "value": "1d"
          },
          {
            "selected": false,
            "text": "2d",
            "value": "2d"
          },
          {
            "selected": false,
            "text": "3d",
            "value": "3d"
          },
          {
            "selected": false,
            "text": "1w",
            "value": "1w"
          }
        ],
        "query": "15m,1h,2h,4h,1d,2d,3d,1w",
        "type": "custom"
      }
    ]
  },
  "time": {
    "from": "now-2h",
    "to": "now"
  },
  "timepicker": {},
  "timezone": "",
  "title": "TokenMM Markouts (v1)",
  "uid": "tokenmm-markouts-v1",
  "version": 2,
  "weekStart": ""
}
